optlang/__init__.py
optlang/_version.py
optlang/coinor_cbc_interface.py
optlang/container.py
optlang/cplex_interface.py
optlang/duality.py
optlang/exceptions.py
optlang/expression_parsing.py
optlang/glpk_exact_interface.py
optlang/glpk_interface.py
optlang/gurobi_interface.py
optlang/hybrid_interface.py
optlang/inspyred_interface.py
optlang/interface.py
optlang/matrix_interface.py
optlang/scipy_interface.py
optlang/symbolics.py
optlang/util.py
optlang/tests/__init__.py
optlang/tests/abstract_test_cases.py
optlang/tests/test_change_solver.py
optlang/tests/test_coinor_cbc_interface.py
optlang/tests/test_container.py
optlang/tests/test_cplex_interface.py
optlang/tests/test_duality.py
optlang/tests/test_elements.py
optlang/tests/test_expression_parsing.py
optlang/tests/test_glpk_exact_interface.py
optlang/tests/test_glpk_interface.py
optlang/tests/test_gurobi_interface.py
optlang/tests/test_hybrid_interface.py
optlang/tests/test_inspyred_interface.py
optlang/tests/test_interface.py
optlang/tests/test_io.py
optlang/tests/test_scipy_interface.py
optlang/tests/test_symbolics.py
optlang/tests/test_util.py
optlang/tests/data/__init__.py
optlang/tests/data/parse_the_final_netlib_results.py
optlang-1.8.2.dist-info/LICENSE
optlang-1.8.2.dist-info/METADATA
optlang-1.8.2.dist-info/WHEEL
optlang-1.8.2.dist-info/top_level.txt
optlang-1.8.2.dist-info/zip-safe
optlang-1.8.2.dist-info/RECORD
