Metadata-Version: 2.1
Name: optlang
Version: 1.8.2
Summary: Formulate optimization problems using sympy expressions and solve them using interfaces to third-party optimization software (e.g. GLPK).
Home-page: https://github.com/opencobra/optlang
Download-URL: https://pypi.org/project/optlang/
Author: Nikolaus Sonnenschein
Author-email: niko.sonnenschein@gmail.com
License: Apache-2.0
Project-URL: Source Code, https://github.com/opencobra/optlang
Project-URL: Documentation, https://optlang.readthedocs.io
Project-URL: Bug Tracker, https://github.com/opencobra/optlang/issues
Keywords: optimization,mathematical programming,heuristic optimization,sympy
Classifier: Development Status :: 5 - Production/Stable
Classifier: Intended Audience :: Science/Research
Classifier: License :: OSI Approved :: Apache Software License
Classifier: Natural Language :: English
Classifier: Operating System :: OS Independent
Classifier: Programming Language :: Python :: 3.8
Classifier: Programming Language :: Python :: 3.9
Classifier: Programming Language :: Python :: 3.10
Classifier: Programming Language :: Python :: 3.11
Classifier: Topic :: Scientific/Engineering :: Mathematics
Requires-Python: >=3.8
License-File: LICENSE
Requires-Dist: swiglpk>=5.0.8
Requires-Dist: sympy>=1.12.0
Provides-Extra: development
Requires-Dist: black; extra == "development"
Requires-Dist: isort; extra == "development"
Requires-Dist: tox; extra == "development"
